isONform-0.3.9.data/scripts/isONform_parallel
isONform-0.3.9.data/scripts/main
modules/GraphGeneration.py
modules/IsoformGeneration.py
modules/Parallelization_side_functions.py
modules/SimplifyGraph.py
modules/__init__.py
modules/batch_merging_parallel.py
modules/consensus.py
modules/create_augmented_reference.py
modules/help_functions.py
isONform-0.3.9.dist-info/LICENSE
isONform-0.3.9.dist-info/METADATA
isONform-0.3.9.dist-info/WHEEL
isONform-0.3.9.dist-info/top_level.txt
isONform-0.3.9.dist-info/RECORD
