Metadata-Version: 2.1
Name: isONform
Version: 0.3.9
Summary: De novo construction of isoforms from long-read data 
Home-page: https://github.com/aljpetri/isONform
Author: Alexander Petri
Author-email: alexander.petri@math.su.se
Keywords: Oxford Nanopore isoform prediction,Pacific Biosciences isoform prediction
Classifier: Development Status :: 3 - Alpha
Classifier: Programming Language :: Python :: 3.7
Classifier: Programming Language :: Python :: 3.8
Classifier: Programming Language :: Python :: 3.9
Classifier: Programming Language :: Python :: 3.10
Classifier: Programming Language :: Python :: 3.11
Requires-Python: >=3.7
License-File: LICENSE
Requires-Dist: recordclass>=0.17.2
Requires-Dist: networkx>=2.7.1
Requires-Dist: parasail>=1.3.3
Requires-Dist: edlib>=1.1.2
